poetry_codeartifact_login/__init__.py
poetry_codeartifact_login/plugin.py
poetry_codeartifact_login-0.3.0.dist-info/METADATA
poetry_codeartifact_login-0.3.0.dist-info/WHEEL
poetry_codeartifact_login-0.3.0.dist-info/entry_points.txt
poetry_codeartifact_login-0.3.0.dist-info/RECORD
