Metadata-Version: 2.3
Name: poetry-codeartifact-login
Version: 0.3.0
Summary: Poetry plugin for logging in to AWS CodeArtifact.
Author: Translucence Biosystems
Requires-Python: >=3.7,<4.0
Classifier: Programming Language :: Python :: 3
Classifier: Programming Language :: Python :: 3.7
Classifier: Programming Language :: Python :: 3.8
Classifier: Programming Language :: Python :: 3.9
Classifier: Programming Language :: Python :: 3.10
Classifier: Programming Language :: Python :: 3.11
Classifier: Programming Language :: Python :: 3.12
Classifier: Programming Language :: Python :: 3.13
Requires-Dist: boto3 (>=1.24.82,<2.0.0)
Requires-Dist: poetry (>=1.2.1,<=3.0.0)
